cosmology/compat/camb/__init__.py
cosmology/compat/camb/py.typed
cosmology_compat_camb-0.2.0.dist-info/METADATA
cosmology_compat_camb-0.2.0.dist-info/WHEEL
cosmology_compat_camb-0.2.0.dist-info/licenses/LICENSE.txt
cosmology_compat_camb-0.2.0.dist-info/RECORD
